scicolor/__init__.py
scicolor/cet_colors/cwr.txt
scicolor/cet_colors/glasbey.txt
scicolor/cet_colors/isolum.txt
scicolor/ocean_colors/topo.txt
scicolor/scientific_colors/acton.txt
scicolor/scientific_colors/acton10.txt
scicolor/scientific_colors/acton25.txt
scicolor/scientific_colors/bamako.txt
scicolor/scientific_colors/batlow.txt
scicolor/scientific_colors/batlow10.txt
scicolor/scientific_colors/batlow25.txt
scicolor/scientific_colors/batlowS.txt
scicolor/scientific_colors/bilbao.txt
scicolor/scientific_colors/broc.txt
scicolor/scientific_colors/broc10.txt
scicolor/scientific_colors/broc25.txt
scicolor/scientific_colors/buda.txt
scicolor/scientific_colors/cork.txt
scicolor/scientific_colors/davos.txt
scicolor/scientific_colors/devon.txt
scicolor/scientific_colors/grayC.txt
scicolor/scientific_colors/imola.txt
scicolor/scientific_colors/lajolla.txt
scicolor/scientific_colors/lapaz.txt
scicolor/scientific_colors/lipari.txt
scicolor/scientific_colors/managua.txt
scicolor/scientific_colors/navia.txt
scicolor/scientific_colors/nuuk.txt
scicolor/scientific_colors/oleron.txt
scicolor/scientific_colors/oleron10.txt
scicolor/scientific_colors/oleron25.txt
scicolor/scientific_colors/oslo.txt
scicolor/scientific_colors/oslo10.txt
scicolor/scientific_colors/oslo25.txt
scicolor/scientific_colors/roma.txt
scicolor/scientific_colors/roma10.txt
scicolor/scientific_colors/roma25.txt
scicolor/scientific_colors/turku.txt
scicolor/scientific_colors/turku10.txt
scicolor/scientific_colors/turku25.txt
scicolor/scientific_colors/vik.txt
scicolor/scientific_colors/vik10.txt
scicolor/scientific_colors/vik25.txt
scicolor-1.3.dist-info/METADATA
scicolor-1.3.dist-info/WHEEL
scicolor-1.3.dist-info/RECORD
