Metadata-Version: 2.4
Name: scicolor
Version: 1.3
Summary: Collections of color maps for scientific visualizations
Project-URL: Homepage, https://github.com/yang3kc/scicolor
Project-URL: Repository, https://github.com/yang3kc/scicolor
Author-email: Kaicheng Yang <yang3kc@gmail.com>
License: MIT
Requires-Python: >=3.8
Requires-Dist: matplotlib
Requires-Dist: numpy
Requires-Dist: pandas
